stoa/__init__.py
stoa/env_types.py
stoa/environment.py
stoa/spaces.py
stoa/stoa_struct.py
stoa/core_wrappers/auto_reset.py
stoa/core_wrappers/episode_metrics.py
stoa/core_wrappers/optimistic_auto_reset.py
stoa/core_wrappers/vmap.py
stoa/core_wrappers/wrapper.py
stoa/env_adapters/base.py
stoa/env_adapters/brax.py
stoa/env_adapters/gymnax.py
stoa/env_adapters/jumanji.py
stoa/env_adapters/kinetix.py
stoa/env_adapters/navix.py
stoa/env_adapters/pgx.py
stoa/env_adapters/playground.py
stoa/env_adapters/xminigrid.py
stoa/tests/spaces_test.py
stoa/utility_wrappers/action_space_transforms.py
stoa/utility_wrappers/extras_transforms.py
stoa/utility_wrappers/flatten_obs.py
stoa/utility_wrappers/frame_stacking.py
stoa/utility_wrappers/obs_extract.py
stoa/utility_wrappers/obs_transforms.py
stoa/utility_wrappers/step_limit.py
stoa_env-0.1.2.dist-info/licenses/LICENSE
stoa_env-0.1.2.dist-info/METADATA
stoa_env-0.1.2.dist-info/WHEEL
stoa_env-0.1.2.dist-info/top_level.txt
stoa_env-0.1.2.dist-info/RECORD
