Metadata-Version: 2.4
Name: stoa-env
Version: 0.1.2
Summary: Single-Agent Reinforcement Learning with JAX
Author: Edan Toledo
License: MIT License
Project-URL: Homepage, https://github.com/EdanToledo/Stoa
Project-URL: Bug Tracker, https://github.com/EdanToledo/Stoa/issues
Classifier: Development Status :: 3 - Alpha
Classifier: Environment :: Console
Classifier: Intended Audience :: Science/Research
Classifier: Intended Audience :: Developers
Classifier: Operating System :: OS Independent
Classifier: Programming Language :: Python :: 3.10
Classifier: Topic :: Scientific/Engineering :: Artificial Intelligence
Classifier: Topic :: Software Development :: Libraries :: Python Modules
Classifier: License :: OSI Approved :: MIT License
Requires-Python: >=3.10
License-File: LICENSE
Requires-Dist: chex>=0.1.89
Requires-Dist: flax>=0.10.5
Requires-Dist: jax>=0.4.25
Requires-Dist: jaxlib>=0.5.3
Requires-Dist: numpy>=1.26.4
Provides-Extra: brax
Requires-Dist: brax>=0.9.0; extra == "brax"
Provides-Extra: gymnax
Requires-Dist: gymnax>=0.0.6; extra == "gymnax"
Requires-Dist: gymnasium>=1.1.1; extra == "gymnax"
Provides-Extra: jumanji
Requires-Dist: jumanji>=1.1.1; extra == "jumanji"
Provides-Extra: kinetix
Requires-Dist: kinetix-env; extra == "kinetix"
Provides-Extra: navix
Requires-Dist: navix>=0.7.0; extra == "navix"
Provides-Extra: pgx
Requires-Dist: pgx>=2.6.0; extra == "pgx"
Provides-Extra: xminigrid
Requires-Dist: xminigrid; extra == "xminigrid"
Provides-Extra: all
Requires-Dist: stoa-env[brax]; extra == "all"
Requires-Dist: stoa-env[gymnax]; extra == "all"
Requires-Dist: stoa-env[jumanji]; extra == "all"
Requires-Dist: stoa-env[kinetix]; extra == "all"
Requires-Dist: stoa-env[navix]; extra == "all"
Requires-Dist: stoa-env[pgx]; extra == "all"
Requires-Dist: stoa-env[xminigrid]; extra == "all"
Provides-Extra: dev
Requires-Dist: black; extra == "dev"
Requires-Dist: coverage; extra == "dev"
Requires-Dist: flake8; extra == "dev"
Requires-Dist: importlib-metadata; extra == "dev"
Requires-Dist: isort; extra == "dev"
Requires-Dist: livereload; extra == "dev"
Requires-Dist: mkdocs; extra == "dev"
Requires-Dist: mkdocs-git-revision-date-plugin; extra == "dev"
Requires-Dist: mkdocs-include-markdown-plugin; extra == "dev"
Requires-Dist: mkdocs-material; extra == "dev"
Requires-Dist: mkdocs-mermaid2-plugin; extra == "dev"
Requires-Dist: mkdocstrings; extra == "dev"
Requires-Dist: mknotebooks; extra == "dev"
Requires-Dist: mypy; extra == "dev"
Requires-Dist: nbmake; extra == "dev"
Requires-Dist: pre-commit; extra == "dev"
Requires-Dist: promise; extra == "dev"
Requires-Dist: pymdown-extensions; extra == "dev"
Requires-Dist: pytest; extra == "dev"
Requires-Dist: pytest-cov; extra == "dev"
Requires-Dist: pytest-mock; extra == "dev"
Requires-Dist: pytest-parallel; extra == "dev"
Requires-Dist: pytest-xdist; extra == "dev"
Requires-Dist: pytype; extra == "dev"
Requires-Dist: testfixtures; extra == "dev"
Dynamic: license-file
